oeis.py
oeis-2023.3.10.dist-info/AUTHORS
oeis-2023.3.10.dist-info/LICENSE
oeis-2023.3.10.dist-info/METADATA
oeis-2023.3.10.dist-info/WHEEL
oeis-2023.3.10.dist-info/entry_points.txt
oeis-2023.3.10.dist-info/top_level.txt
oeis-2023.3.10.dist-info/RECORD
