Metadata-Version: 2.1
Name: oeis
Version: 2023.3.10
Summary: Implementation of a few integer sequences from the OEIS.
Author-email: Julien Palard <julien@palard.fr>
License: MIT License
Project-URL: homepage, https://github.com/JulienPalard/oeis
Classifier: Development Status :: 5 - Production/Stable
Classifier: Intended Audience :: Developers
Classifier: License :: OSI Approved :: MIT License
Classifier: Natural Language :: English
Classifier: Programming Language :: Python :: 3
Requires-Python: >=3.7
License-File: LICENSE
License-File: AUTHORS
Requires-Dist: matplotlib (<4,>=3.1)
Requires-Dist: sympy (<2,>=1.2)
